{
  "$schema": "https://developer.microsoft.com/json-schemas/fabric/item/report/definition/visualContainer/2.10.0/schema.json",
  "name": "282df49954f0274e28d1",
  "position": {
    "x": 0,
    "y": 102.52427184466021,
    "z": 3000,
    "height": 154.30420711974111,
    "width": 236.11650485436894,
    "tabOrder": 3000
  },
  "visual": {
    "visualType": "slicer",
    "query": {
      "queryState": {
        "Values": {
          "projections": [
            {
              "field": {
                "Column": {
                  "Expression": {
                    "SourceRef": {
                      "Entity": "納入品目_値上げイベント"
                    }
                  },
                  "Property": "F_納入品目番号"
                }
              },
              "queryRef": "納入品目_値上げイベント.F_納入品目番号",
              "nativeQueryRef": "F_納入品目番号",
              "active": true
            }
          ]
        }
      }
    },
    "objects": {
      "data": [
        {
          "properties": {
            "mode": {
              "expr": {
                "Literal": {
                  "Value": "'Basic'"
                }
              }
            }
          }
        }
      ],
      "general": [
        {
          "properties": {
            "selfFilterEnabled": {
              "expr": {
                "Literal": {
                  "Value": "true"
                }
              }
            }
          }
        }
      ],
      "items": [
        {
          "properties": {
            "textSize": {
              "expr": {
                "Literal": {
                  "Value": "10D"
                }
              }
            }
          }
        }
      ]
    },
    "drillFilterOtherVisuals": true
  }
}