{
  "$schema": "https://developer.microsoft.com/json-schemas/fabric/item/report/definition/visualContainer/2.10.0/schema.json",
  "name": "6245739a3375f345a5d2",
  "position": {
    "x": 137.48743718592965,
    "y": 136.28140703517587,
    "z": 8000,
    "height": 243.6180904522613,
    "width": 142.31155778894473,
    "tabOrder": 8000
  },
  "visual": {
    "visualType": "slicer",
    "query": {
      "queryState": {
        "Values": {
          "projections": [
            {
              "field": {
                "Column": {
                  "Expression": {
                    "SourceRef": {
                      "Entity": "品目分類情報"
                    }
                  },
                  "Property": "F_分類名"
                }
              },
              "queryRef": "品目分類情報.F_分類名",
              "nativeQueryRef": "F_分類名",
              "active": true
            }
          ]
        }
      }
    },
    "objects": {
      "data": [
        {
          "properties": {
            "mode": {
              "expr": {
                "Literal": {
                  "Value": "'Basic'"
                }
              }
            }
          }
        }
      ],
      "general": [
        {
          "properties": {
            "selfFilterEnabled": {
              "expr": {
                "Literal": {
                  "Value": "true"
                }
              }
            },
            "filter": {
              "filter": {
                "Version": 2,
                "From": [
                  {
                    "Name": "品",
                    "Entity": "品目分類情報",
                    "Type": 0
                  }
                ],
                "Where": [
                  {
                    "Condition": {
                      "In": {
                        "Expressions": [
                          {
                            "Column": {
                              "Expression": {
                                "SourceRef": {
                                  "Source": "品"
                                }
                              },
                              "Property": "F_分類名"
                            }
                          }
                        ],
                        "Values": [
                          [
                            {
                              "Literal": {
                                "Value": "'テ－プ類'"
                              }
                            }
                          ],
                          [
                            {
                              "Literal": {
                                "Value": "'電線材料'"
                              }
                            }
                          ],
                          [
                            {
                              "Literal": {
                                "Value": "'電線類'"
                              }
                            }
                          ]
                        ]
                      }
                    }
                  }
                ]
              }
            }
          }
        }
      ],
      "items": [
        {
          "properties": {
            "textSize": {
              "expr": {
                "Literal": {
                  "Value": "10D"
                }
              }
            }
          }
        }
      ]
    },
    "drillFilterOtherVisuals": true
  },
  "filterConfig": {
    "filters": [
      {
        "name": "c606e455d2b88252f8ac",
        "ordinal": 0,
        "field": {
          "Column": {
            "Expression": {
              "SourceRef": {
                "Entity": "品目分類情報"
              }
            },
            "Property": "F_分類名"
          }
        },
        "type": "Advanced"
      },
      {
        "name": "5c6834d021a17929de95",
        "ordinal": 1,
        "field": {
          "Measure": {
            "Expression": {
              "SourceRef": {
                "Entity": "品目分類情報"
              }
            },
            "Property": "分類使用有無_材料"
          }
        },
        "type": "Advanced",
        "filter": {
          "Version": 2,
          "From": [
            {
              "Name": "品",
              "Entity": "品目分類情報",
              "Type": 0
            }
          ],
          "Where": [
            {
              "Condition": {
                "Comparison": {
                  "ComparisonKind": 0,
                  "Left": {
                    "Measure": {
                      "Expression": {
                        "SourceRef": {
                          "Source": "品"
                        }
                      },
                      "Property": "分類使用有無_材料"
                    }
                  },
                  "Right": {
                    "Literal": {
                      "Value": "1L"
                    }
                  }
                }
              }
            }
          ]
        },
        "howCreated": "User"
      }
    ],
    "filterSortOrder": "Custom"
  }
}